cdb_fan_control/__init__.py
cdb_fan_control/fan_control.py
cdb_fan_control-1.0.1.dist-info/licenses/LICENSE
cdb_fan_control-1.0.1.dist-info/METADATA
cdb_fan_control-1.0.1.dist-info/WHEEL
cdb_fan_control-1.0.1.dist-info/entry_points.txt
cdb_fan_control-1.0.1.dist-info/top_level.txt
cdb_fan_control-1.0.1.dist-info/RECORD
