Metadata-Version: 2.4
Name: cdb-fan-control
Version: 1.0.1
Summary: Simple utility to control Coral Dev Board fan
Author-email: Changhun Han <ehwjs1914@naver.com>
License: MIT License
Classifier: Programming Language :: Python :: 3
Classifier: Operating System :: OS Independent
Classifier: License :: OSI Approved :: MIT License
Requires-Python: <3.10,>=3.7
License-File: LICENSE
Dynamic: license-file
